{
  "books": [
    {
      "title": "Laskar Pelangi",
      "author": "Andrea Hirata",
      "genre": [
        "Fiction",
        "Drama",
        "Friendship"
      ],
      "description": "A novel that tells the story of ten children and their two teachers struggling to learn and make their dreams come true against the backdrop of poverty and prejudice in Belitung, Indonesia.",
      "publishedYear": "2005",
      "id": "32f14257-c128-4239-94ff-864e37292341",
      "createdAt": "2024-01-29T09:39:15.854Z",
      "updatedAt": "2024-02-07T21:20:39.961Z"
    },
    {
      "title": "Pride and Prejudice",
      "author": "Jane Austen",
      "genre": [
        "Romance",
        "Classic Literature"
      ],
      "description": "A romantic novel set in early 19th-century England, revolving around the themes of love, marriage, and societal expectations, primarily focusing on the spirited Elizabeth Bennet and the proud Mr. Darcy.",
      "publishedYear": "1813",
      "id": "ae5f14c5-48e2-44f9-8e5b-2ea01fc787c7",
      "createdAt": "2024-01-29T09:39:30.985Z",
      "updatedAt": "2024-01-29T09:46:18.103Z"
    }
  ]
}